{"elapsed":"0.16","endpoint-url":"https://raw.githubusercontent.com/digital-land/listed-building-collection/main/data/Southwark/Grade%20I%20Star.zip","entry-date":"2023-05-26T00:16:47.872396","request-headers":{"Accept":"*/*","Accept-Encoding":"gzip, deflate","Connection":"keep-alive","User-Agent":"DLUHC Digital Land"},"resource":"e3a22838b44a3c1e594eee33788728a6366caef066690e5fb9fd91e46e74bac1","response-headers":{"Accept-Ranges":"bytes","Access-Control-Allow-Origin":"*","Cache-Control":"max-age=300","Connection":"keep-alive","Content-Length":"11714","Content-Security-Policy":"default-src 'none'; style-src 'unsafe-inline'; sandbox","Content-Type":"application/zip","Date":"Fri, 26 May 2023 00:17:04 GMT","ETag":"W/\"543bfb3611ce7dd0a394cc870097ecf3781e3bf26c8ac8cad5d681796a3a1d62\"","Expires":"Fri, 26 May 2023 00:22:04 GMT","Source-Age":"0","Strict-Transport-Security":"max-age=31536000","Vary":"Authorization,Accept-Encoding,Origin","Via":"1.1 varnish","X-Cache":"MISS","X-Cache-Hits":"0","X-Content-Type-Options":"nosniff","X-Fastly-Request-ID":"88a55eaaa5f1cfe85eab16a0b7ab744fb54af712","X-Frame-Options":"deny","X-GitHub-Request-Id":"D0A6:3E92:C86E1A:EAA68A:646FFA7F","X-Served-By":"cache-sjc1000115-SJC","X-Timer":"S1685060224.926031,VS0,VE155","X-XSS-Protection":"1; mode=block"},"ssl-verify":true,"status":"200"}