{"elapsed":"0.261","endpoint-url":"https://raw.githubusercontent.com/digital-land/listed-building-collection/main/data/Southwark/Grade%20I.zip","entry-date":"2022-07-06T00:19:29.177526","request-headers":{"Accept":"*/*","Accept-Encoding":"gzip, deflate","Connection":"keep-alive","User-Agent":"DLUHC Digital Land"},"resource":"9d20207f8f2f674fda09b9632bd5d1495a635fcb762827b46c96522a45624bff","response-headers":{"Accept-Ranges":"bytes","Access-Control-Allow-Origin":"*","Cache-Control":"max-age=300","Connection":"keep-alive","Content-Length":"5730","Content-Security-Policy":"default-src 'none'; style-src 'unsafe-inline'; sandbox","Content-Type":"application/zip","Date":"Wed, 06 Jul 2022 00:19:43 GMT","ETag":"W/\"bf1301f1467786bdbd5f5397b9365dcdca020ac2611cc68d25ca6f7fc6840847\"","Expires":"Wed, 06 Jul 2022 00:24:43 GMT","Source-Age":"0","Strict-Transport-Security":"max-age=31536000","Vary":"Authorization,Accept-Encoding,Origin","Via":"1.1 varnish","X-Cache":"MISS","X-Cache-Hits":"0","X-Content-Type-Options":"nosniff","X-Fastly-Request-ID":"639905375624eb5afb7966f83cbc59b3e5ffc2c1","X-Frame-Options":"deny","X-GitHub-Request-Id":"0E34:6210:012B:01EA:62C4D51F","X-Served-By":"cache-bur-kbur8200131-BUR","X-Timer":"S1657066783.207101,VS0,VE247","X-XSS-Protection":"1; mode=block"},"ssl-verify":true,"status":"200"}