{"elapsed":"0.122","endpoint-url":"https://raw.githubusercontent.com/digital-land/listed-building-collection/main/data/Southwark/Grade%20I%20Star.zip","entry-date":"2022-03-03T00:20:50.215052","request-headers":{"Accept":"*/*","Accept-Encoding":"gzip, deflate","Connection":"keep-alive","User-Agent":"DLUHC Digital Land"},"resource":"e3a22838b44a3c1e594eee33788728a6366caef066690e5fb9fd91e46e74bac1","response-headers":{"Accept-Ranges":"bytes","Access-Control-Allow-Origin":"*","Cache-Control":"max-age=300","Connection":"keep-alive","Content-Length":"11714","Content-Security-Policy":"default-src 'none'; style-src 'unsafe-inline'; sandbox","Content-Type":"application/zip","Date":"Thu, 03 Mar 2022 00:21:01 GMT","ETag":"W/\"543bfb3611ce7dd0a394cc870097ecf3781e3bf26c8ac8cad5d681796a3a1d62\"","Expires":"Thu, 03 Mar 2022 00:26:01 GMT","Source-Age":"0","Strict-Transport-Security":"max-age=31536000","Vary":"Authorization,Accept-Encoding,Origin","Via":"1.1 varnish","X-Cache":"MISS","X-Cache-Hits":"0","X-Content-Type-Options":"nosniff","X-Fastly-Request-ID":"38e2114faf2704fd3072fab8c52e0445f43130bd","X-Frame-Options":"deny","X-GitHub-Request-Id":"B3AE:38DA:171B1:22910:622009ED","X-Served-By":"cache-iad-kiad7000072-IAD","X-Timer":"S1646266861.425419,VS0,VE114","X-XSS-Protection":"1; mode=block"},"ssl-verify":true,"status":"200"}