{"elapsed":"0.729","endpoint-url":"https://services7.arcgis.com/gTvs0fY5s2kJG3gO/arcgis/rest/services/SPE_Listed_Buildings/FeatureServer/3/query?outFields=*&where=1%3D1&f=geojson","entry-date":"2023-12-21T00:16:34.415399","request-headers":{"Accept":"*/*","Accept-Encoding":"gzip, deflate","Connection":"keep-alive","User-Agent":"DLUHC Digital Land"},"resource":"dd6c3678a9df12bd7836e7cf50bbbadc79e26420352a299db9eeb8f37d54734b","response-headers":{"Access-Control-Allow-Origin":"*","Cache-Control":"public, max-age=30, s-maxage=30","Connection":"keep-alive","Content-Encoding":"gzip","Content-Length":"130966","Content-Type":"application/json; charset=utf-8","Date":"Thu, 21 Dec 2023 00:20:05 GMT","ETag":"sd728_633272742","Last-Modified":"Tue, 28 Nov 2023 09:41:20 GMT","Request-Context":"appId=cid-v1:e760746d-7077-47f1-a125-f6cc9f1bba28","Vary":"X-Esri-Authorization","Via":"1.1 1a201df35abe730337e131d797c8f688.cloudfront.net (CloudFront)","X-Amz-Cf-Id":"jkn_7paCkN8I3Krnqd_XYPRpefyKRR3ULpaUegaQu7_h-T0JItnENg==","X-Amz-Cf-Pop":"SFO53-P3","X-ArcGIS-Correlation-Id":"00-d3492d1836470f1950220586cc78ee51-1c088fc370c50450-00","X-ArcGIS-Instance":"lf3xzxihb000008","X-ArcGIS-Trace-Id":"d3492d1836470f1950220586cc78ee51","X-Cache":"Miss from cloudfront","x-arcgis-upstream":"us1h07c00","x-esri-org-request-units-per-min":"usage=2;max=6000","x-esri-query-geometry-field-name":"Shape","x-esri-query-max-vertex-count":"889","x-esri-query-request-units":"2","x-esri-tiles-basic-query-mode":"true","x-esri-tiles-basic-query-type":"Basic"},"ssl-verify":true,"status":"200"}