{"elapsed":"1.571","endpoint-url":"https://datamillnorth.org/download/listedbuildings/91298d09-45a6-4c6d-a909-11ec4eaab957/listedbuildings.csv","entry-date":"2023-09-26T00:17:40.915993","request-headers":{"Accept":"*/*","Accept-Encoding":"gzip, deflate","Connection":"keep-alive","User-Agent":"DLUHC Digital Land"},"resource":"6aba6abf34a427aa95cb105abcfd570d713299e75477871e403009aa05f33681","response-headers":{"accept-ranges":"bytes","content-length":"1601652","content-type":"text/csv","date":"Tue, 26 Sep 2023 00:18:19 GMT","etag":"\"a0de7a7dcfa885346e9e48f9cf4a3c4a\"","last-modified":"Sun, 27 Aug 2023 18:54:22 GMT","strict-transport-security":"max-age=15552000; includeSubDomains; preload","vary":"Origin, Access-Control-Request-Headers, Access-Control-Request-Method","x-amz-meta-mtime":"1655196000","x-amz-request-id":"tx000000000000013990c2a-006512234b-40ef8e33-ams3b","x-envoy-upstream-healthchecked-cluster":"","x-rgw-object-type":"Normal"},"ssl-verify":true,"status":"200"}