{"elapsed":"0.123","endpoint-url":"https://raw.githubusercontent.com/digital-land/historic-england-collection/main/data/listed-building-grade.csv","entry-date":"2021-11-03T00:41:05.336869","request-headers":{"Accept":"*/*","Accept-Encoding":"gzip, deflate","Connection":"keep-alive","User-Agent":"Digital Land"},"response-headers":{"Accept-Ranges":"bytes","Access-Control-Allow-Origin":"*","Connection":"keep-alive","Content-Length":"14","Content-Security-Policy":"default-src 'none'; style-src 'unsafe-inline'; sandbox","Content-Type":"text/plain; charset=utf-8","Date":"Wed, 03 Nov 2021 00:41:05 GMT","Expires":"Wed, 03 Nov 2021 00:46:05 GMT","Source-Age":"0","Strict-Transport-Security":"max-age=31536000","Vary":"Authorization,Accept-Encoding,Origin","Via":"1.1 varnish","X-Cache":"MISS","X-Cache-Hits":"0","X-Content-Type-Options":"nosniff","X-Fastly-Request-ID":"0a26d0167fe58bb697f5972836755345881ed5da","X-Frame-Options":"deny","X-GitHub-Request-Id":"10D2:51B0:10DD1F:15061C:6181DAA1","X-Served-By":"cache-bwi5035-BWI","X-Timer":"S1635900066.751548,VS0,VE84","X-XSS-Protection":"1; mode=block"},"ssl-verify":true,"status":"404"}